DjTbot/__init__.py
DjTbot/admin.py
DjTbot/arguments.py
DjTbot/commands.py
DjTbot/models.py
DjTbot/utils.py
DjTbot/core/__init__.py
DjTbot/core/argumentparser.py
DjTbot/core/commands.py
DjTbot/core/errors.py
DjTbot/core/giphy.py
DjTbot/core/listeners.py
DjTbot/core/network.py
DjTbot/core/telegram_lib.py
DjTbot/management/__init__.py
DjTbot/management/commands/__init__.py
DjTbot/management/commands/addgroup.py
DjTbot/management/commands/adduser.py
DjTbot/management/commands/addusertogroup.py
DjTbot/management/commands/clear_api_key.py
DjTbot/management/commands/createbotadmin.py
DjTbot/management/commands/lsgroups.py
DjTbot/management/commands/lsusers.py
DjTbot/management/commands/removeuserfromgroup.py
DjTbot/management/commands/rmgroup.py
DjTbot/management/commands/rmuser.py
DjTbot/management/commands/runbot.py
DjTbot/management/commands/sendmessage.py
DjTbot/migrations/0001_initial.py
DjTbot/migrations/__init__.py
DjTbot-0.0.7.dist-info/METADATA
DjTbot-0.0.7.dist-info/WHEEL
DjTbot-0.0.7.dist-info/top_level.txt
DjTbot-0.0.7.dist-info/RECORD
