Metadata-Version: 2.1
Name: DjTbot
Version: 0.0.7
Summary: Django Telegram Bot
Home-page: https://git.herrerosolis.com/bots/DjTbot
Download-URL: https://git.herrerosolis.com/bots/DjTbot/-/archive/master/DjTbot-master.tar.gz
Author: Rafael Herrero Solis
Author-email: rafahsolis@hotmail.com
License: License :: OSI Approved :: MIT License
Keywords: Django,Telegram,Bot
Classifier: License :: OSI Approved :: MIT License
Classifier: Development Status :: 3 - Alpha
Classifier: License :: OSI Approved :: Apache Software License
Classifier: Programming Language :: Python :: 3.6
Requires-Dist: CheKnife (>=0.0.7)
Requires-Dist: python-telegram-bot (>=12.2.0)
Requires-Dist: Django (>=3.0)
Requires-Dist: future (>=0.16.0)
